{
  "courses": [
    {
      "id": "1",
      "department": "Ballet",
      "level": 3,
      "students": [
        {
          "id": 1,
          "name": "Angel Trevino",
          "email": "wperry@example.org"
        },
        {
          "id": 2,
          "name": "Gregg Williams",
          "email": "melvin69@example.com"
        },
        {
          "id": 3,
          "name": "Whitney Knapp",
          "email": "cunninghamlisa@example.org"
        },
        {
          "id": 4,
          "name": "Mrs. Alexandria Rodriguez",
          "email": "yangcharles@example.net"
        },
        {
          "id": 6,
          "name": "Andrea Obrien",
          "email": "tbryant@example.com"
        }
      ],
      "report_text": "This is a report about Ballet 3, and what we did this semester!"
    },
    {
      "id": "2",
      "department": "Jazz",
      "level": 4,
      "students": [
        {
          "id": 1,
          "name": "Angel Trevino",
          "email": "wperry@example.org"
        },
        {
          "id": 3,
          "name": "Whitney Knapp",
          "email": "cunninghamlisa@example.org"
        },
        {
          "id": 4,
          "name": "Mrs. Alexandria Rodriguez",
          "email": "yangcharles@example.net"
        },
        {
          "id": 5,
          "name": "John Robertson",
          "email": "tara87@example.org"
        },
        {
          "id": 6,
          "name": "Andrea Obrien",
          "email": "tbryant@example.com"
        },
        {
          "id": 7,
          "name": "Nathan Crawford",
          "email": "jamesholmes@example.com"
        },
        {
          "id": 9,
          "name": "Lauren Sullivan",
          "email": "leblancnancy@example.net"
        }
      ]
    },
    {
      "id": "3",
      "department": "Tap",
      "level": 2,
      "students": [
        {
          "id": 2,
          "name": "Gregg Williams",
          "email": "melvin69@example.com"
        },
        {
          "id": 3,
          "name": "Whitney Knapp",
          "email": "cunninghamlisa@example.org"
        },
        {
          "id": 4,
          "name": "Mrs. Alexandria Rodriguez",
          "email": "yangcharles@example.net"
        },
        {
          "id": 6,
          "name": "Andrea Obrien",
          "email": "tbryant@example.com"
        },
        {
          "id": 7,
          "name": "Nathan Crawford",
          "email": "jamesholmes@example.com"
        },
        {
          "id": 9,
          "name": "Lauren Sullivan",
          "email": "leblancnancy@example.net"
        }
      ]
    },
    {
      "id": "4",
      "department": "Hip Hop",
      "level": 8,
      "students": [
        {
          "id": 1,
          "name": "Angel Trevino",
          "email": "wperry@example.org"
        },
        {
          "id": 2,
          "name": "Gregg Williams",
          "email": "melvin69@example.com"
        },
        {
          "id": 3,
          "name": "Whitney Knapp",
          "email": "cunninghamlisa@example.org"
        },
        {
          "id": 4,
          "name": "Mrs. Alexandria Rodriguez",
          "email": "yangcharles@example.net"
        },
        {
          "id": 5,
          "name": "John Robertson",
          "email": "tara87@example.org"
        }
      ]
    }
  ],
  "students": [
    {
      "id": "1",
      "name": "Angel Trevino",
      "email": "wperry@example.org"
    },
    {
      "id": "2",
      "name": "Gregg Williams",
      "email": "melvin69@example.com"
    },
    {
      "id": "3",
      "name": "Whitney Knapp",
      "email": "cunninghamlisa@example.org"
    },
    {
      "id": "4",
      "name": "Mrs. Alexandria Rodriguez",
      "email": "yangcharles@example.net"
    },
    {
      "id": "5",
      "name": "John Robertson",
      "email": "tara87@example.org"
    },
    {
      "id": "6",
      "name": "Andrea Obrien",
      "email": "tbryant@example.com"
    },
    {
      "id": "7",
      "name": "Nathan Crawford",
      "email": "jamesholmes@example.com"
    },
    {
      "id": "8",
      "name": "Christine Arellano",
      "email": "kellertrevor@example.com"
    },
    {
      "id": "9",
      "name": "Lauren Sullivan",
      "email": "leblancnancy@example.net"
    },
    {
      "id": "10",
      "name": "Samantha Johnson",
      "email": "nhernandez@example.org"
    }
  ],
  "reports": [
    {
      "id": "1",
      "course_id": 1,
      "student_id": 1,
      "course_name": "Ballet 3",
      "student_name": "Angel Trevino",
      "report_text": ""
    },
    {
      "id": "2",
      "course_id": 1,
      "student_id": 2,
      "course_name": "Ballet 3",
      "student_name": "Gregg Williams",
      "report_text": "Like speech technology behavior yeah. Identify have theory process amount boy state. Stage usually morning someone feel."
    },
    {
      "id": "3",
      "course_id": 1,
      "student_id": 3,
      "course_name": "Ballet 3",
      "student_name": "Whitney Knapp",
      "report_text": "Number cup month foreign name throughout culture. Lay prove politics must recent film. Sing use foot act fall sign measure."
    },
    {
      "id": "4",
      "course_id": 1,
      "student_id": 4,
      "course_name": "Ballet 3",
      "student_name": "Mrs. Alexandria Rodriguez",
      "report_text": "Item television kitchen report. Thus ask else Mr term."
    },
    {
      "id": "5",
      "course_id": 1,
      "student_id": 6,
      "course_name": "Ballet 3",
      "student_name": "Andrea Obrien",
      "report_text": "Just development writer need remain think. Newspaper food land building those might left."
    },
    {
      "id": "6",
      "course_id": 2,
      "student_id": 1,
      "course_name": "Jazz 4",
      "student_name": "Angel Trevino",
      "report_text": "Argue against environmental. View issue responsibility look ability. Not fish soldier per."
    },
    {
      "id": "7",
      "course_id": 2,
      "student_id": 3,
      "course_name": "Jazz 4",
      "student_name": "Whitney Knapp",
      "report_text": "Notice admit determine night tend modern. Book live significant north. Wear herself series despite then enter window middle."
    },
    {
      "id": "8",
      "course_id": 2,
      "student_id": 4,
      "course_name": "Jazz 4",
      "student_name": "Mrs. Alexandria Rodriguez",
      "report_text": "When kind reality agreement protect. Others degree spring check."
    },
    {
      "id": "9",
      "course_id": 2,
      "student_id": 5,
      "course_name": "Jazz 4",
      "student_name": "John Robertson",
      "report_text": "Today service assume fact successful paper article peace. Court her traditional watch hour billion. Call about but instead."
    },
    {
      "id": "10",
      "course_id": 2,
      "student_id": 6,
      "course_name": "Jazz 4",
      "student_name": "Andrea Obrien",
      "report_text": "Stock form mean loss mother. Subject Mrs draw local drug."
    },
    {
      "id": "11",
      "course_id": 2,
      "student_id": 7,
      "course_name": "Jazz 4",
      "student_name": "Nathan Crawford",
      "report_text": "Win fast phone while treatment. Smile arm agent sit choice right trade."
    },
    {
      "id": "12",
      "course_id": 2,
      "student_id": 9,
      "course_name": "Jazz 4",
      "student_name": "Lauren Sullivan",
      "report_text": "Lauren Sullivan."
    },
    {
      "id": "13",
      "course_id": 3,
      "student_id": 2,
      "course_name": "Tap 2",
      "student_name": "Gregg Williams",
      "report_text": "Teacher those since hard politics. Wife total health subject feel tell."
    },
    {
      "id": "14",
      "course_id": 3,
      "student_id": 3,
      "course_name": "Tap 2",
      "student_name": "Whitney Knapp",
      "report_text": "Senior sound suggest movie after answer. Realize through participant usually. Act close window agreement."
    },
    {
      "id": "15",
      "course_id": 3,
      "student_id": 4,
      "course_name": "Tap 2",
      "student_name": "Mrs. Alexandria Rodriguez",
      "report_text": "Space model experience car seven bring. Share mind do usually."
    },
    {
      "id": "16",
      "course_id": 3,
      "student_id": 6,
      "course_name": "Tap 2",
      "student_name": "Andrea Obrien",
      "report_text": "Growth ten recognize. Field next strong so draw sister. Actually street citizen serious notice expect."
    },
    {
      "id": "17",
      "course_id": 3,
      "student_id": 7,
      "course_name": "Tap 2",
      "student_name": "Nathan Crawford",
      "report_text": "Back environment summer fine. Others paper sea church change science by. Church perhaps difficult success marriage imagine. Song different check thousand these better."
    },
    {
      "id": "18",
      "course_id": 3,
      "student_id": 9,
      "course_name": "Tap 2",
      "student_name": "Lauren Sullivan",
      "report_text": "Eight sister produce son too old with. True produce reach office. Red white continue point share everyone of decide."
    },
    {
      "id": "19",
      "course_id": 4,
      "student_id": 1,
      "course_name": "Hip Hop 8",
      "student_name": "Angel Trevino",
      "report_text": "Fish radio guess. Take yet exist."
    },
    {
      "id": "20",
      "course_id": 4,
      "student_id": 2,
      "course_name": "Hip Hop 8",
      "student_name": "Gregg Williams",
      "report_text": "Turn act share purpose. Five decision feel scene avoid building prepare. May name red risk eye cell."
    },
    {
      "id": "21",
      "course_id": 4,
      "student_id": 3,
      "course_name": "Hip Hop 8",
      "student_name": "Whitney Knapp",
      "report_text": "Money remember far high. Particular camera just year bag option walk. Finally see generation east democratic."
    },
    {
      "id": "22",
      "course_id": 4,
      "student_id": 4,
      "course_name": "Hip Hop 8",
      "student_name": "Mrs. Alexandria Rodriguez",
      "report_text": "From issue evidence face prevent. Society ground fill program. Wide feeling step its."
    },
    {
      "id": "23",
      "course_id": 4,
      "student_id": 5,
      "course_name": "Hip Hop 8",
      "student_name": "John Robertson",
      "report_text": "Upon take miss human. Important after result wall represent piece goal scene. Song picture pull tough."
    }
  ]
}